server.py
mseep_food_delivery_mcp-0.1.3.dist-info/METADATA
mseep_food_delivery_mcp-0.1.3.dist-info/WHEEL
mseep_food_delivery_mcp-0.1.3.dist-info/entry_points.txt
mseep_food_delivery_mcp-0.1.3.dist-info/top_level.txt
mseep_food_delivery_mcp-0.1.3.dist-info/RECORD
